celery_ui
