Metadata-Version: 1.1
Name: celery-ui
Version: 0.0.3
Summary: Execute Celery tasks through a web-based interface
Home-page: https://github.com/mattlong/celery-ui
Author: Matt Long
Author-email: matt@mattlong.org
License: MIT
Download-URL: https://github.com/mattlong/celery-ui/tarball/0.0.3
Platform: UNKNOWN
